microflask/abstract_app.py
microflask/utils.py
microflask/constants/__init__.py
microflask/constants/error_constants.py
microflask/security/__init__.py
microflask/security/generic.py
microflask-1.0.0.dist-info/METADATA
microflask-1.0.0.dist-info/WHEEL
microflask-1.0.0.dist-info/top_level.txt
microflask-1.0.0.dist-info/RECORD
