Metadata-Version: 2.2
Name: microflask
Version: 1.0.0
Summary: This project contains bootstrap code to speed up the development of AWS based microservices
Author: Michael Hudelson
Author-email: michaelhudelson@gmail.com
License: MIT
Requires-Python: >=3.7
Requires-Dist: boto3
Requires-Dist: flask
Requires-Dist: flask-classful
Requires-Dist: redis
Requires-Dist: requests
Dynamic: author
Dynamic: author-email
Dynamic: description
Dynamic: description-content-type
Dynamic: license
Dynamic: requires-dist
Dynamic: requires-python
Dynamic: summary
